llm_json/__init__.py
llm_json/array_extractor.py
llm_json/corrector.py
llm_json/extractor.py
llm_json/types.py
llm_json/validator.py
solvers_hub_llm_json-0.1.2.dist-info/METADATA
solvers_hub_llm_json-0.1.2.dist-info/WHEEL
solvers_hub_llm_json-0.1.2.dist-info/top_level.txt
solvers_hub_llm_json-0.1.2.dist-info/RECORD
