Metadata-Version: 2.4
Name: solvers_hub_llm_json
Version: 0.1.2
Summary: A Python library to extract and correct JSON from LLM outputs
Author-email: Solvers Hub <v.nitish.work@gmail.com>, Nitish <v.nitish.work@gmail.com>
Project-URL: Homepage, https://github.com/solvers-hub/llm-json
Project-URL: Bug Tracker, https://github.com/solvers-hub/llm-json/issues
Classifier: Programming Language :: Python :: 3
Classifier: License :: OSI Approved :: MIT License
Classifier: Operating System :: OS Independent
Requires-Python: >=3.7
Requires-Dist: jsonschema>=4.0.0
